setup.py
gausbinom_distributions/Binomialdistribution.py
gausbinom_distributions/Gaussiandistribution.py
gausbinom_distributions/Generaldistribution.py
gausbinom_distributions/__init__.py
gausbinom_distributions.egg-info/PKG-INFO
gausbinom_distributions.egg-info/SOURCES.txt
gausbinom_distributions.egg-info/dependency_links.txt
gausbinom_distributions.egg-info/not-zip-safe
gausbinom_distributions.egg-info/top_level.txt