Metadata-Version: 1.0
Name: gausbinom-distributions
Version: 0.1
Summary: Gaussian distributions
Home-page: UNKNOWN
Author: Onur Uludag
Author-email: ozu0001@auburn.edu
License: UNKNOWN
Platform: UNKNOWN
